{
  "updated_utc": "2026-07-20T20:17:19+00:00",
  "paper": true,
  "equity": 500219.66,
  "cash": 475000.02,
  "buying_power": 475000.02,
  "starting_equity": 500000.0,
  "drop_threshold_pct": -5.0,
  "sell_threshold_pct": 7.0,
  "positions": [
    {
      "symbol": "CVNA",
      "name": "",
      "qty": 195.46505082,
      "avg_entry_price": 63.95,
      "current_price": 64.1999,
      "unrealized_pl": 48.846716,
      "unrealized_plpc": 0.391
    },
    {
      "symbol": "HONA",
      "name": "",
      "qty": 62.340980499,
      "avg_entry_price": 200.51,
      "current_price": 203.25,
      "unrealized_pl": 170.814286,
      "unrealized_plpc": 1.367
    }
  ]
}