{
  "updated_utc": "2026-07-22T14:51:48+00:00",
  "drop_threshold_pct": -5.0,
  "high_conviction_pct": -8.0,
  "stocks": [
    {
      "symbol": "WDAY",
      "name": "Workday, Inc.",
      "sector": "Information Technology",
      "pct_change": -4.951480898086269,
      "conviction": "watching",
      "status": "watching",
      "news_bad": null
    },
    {
      "symbol": "NOW",
      "name": "ServiceNow",
      "sector": "Information Technology",
      "pct_change": -4.851064586870444,
      "conviction": "watching",
      "status": "watching",
      "news_bad": null
    },
    {
      "symbol": "DASH",
      "name": "DoorDash",
      "sector": "Consumer Discretionary",
      "pct_change": -4.7543009475721325,
      "conviction": "watching",
      "status": "watching",
      "news_bad": null
    },
    {
      "symbol": "PLTR",
      "name": "Palantir Technologies",
      "sector": "Information Technology",
      "pct_change": -4.56429981759847,
      "conviction": "watching",
      "status": "watching",
      "news_bad": null
    },
    {
      "symbol": "TYL",
      "name": "Tyler Technologies",
      "sector": "Information Technology",
      "pct_change": -4.010138588539058,
      "conviction": "watching",
      "status": "watching",
      "news_bad": null
    },
    {
      "symbol": "PTC",
      "name": "PTC Inc.",
      "sector": "Information Technology",
      "pct_change": -3.9786374420269923,
      "conviction": "watching",
      "status": "watching",
      "news_bad": null
    },
    {
      "symbol": "COIN",
      "name": "Coinbase",
      "sector": "Financials",
      "pct_change": -3.741826330777215,
      "conviction": "watching",
      "status": "watching",
      "news_bad": null
    },
    {
      "symbol": "CB",
      "name": "Chubb Limited",
      "sector": "Financials",
      "pct_change": -3.69503545733276,
      "conviction": "watching",
      "status": "watching",
      "news_bad": null
    },
    {
      "symbol": "CVNA",
      "name": "Carvana",
      "sector": "Consumer Discretionary",
      "pct_change": -3.629156757644693,
      "conviction": "watching",
      "status": "watching",
      "news_bad": null
    },
    {
      "symbol": "VEEV",
      "name": "Veeva Systems",
      "sector": "Health Care",
      "pct_change": -3.514060960811828,
      "conviction": "watching",
      "status": "watching",
      "news_bad": null
    },
    {
      "symbol": "DDOG",
      "name": "Datadog",
      "sector": "Information Technology",
      "pct_change": -3.3714025527854763,
      "conviction": "watching",
      "status": "watching",
      "news_bad": null
    },
    {
      "symbol": "TRMB",
      "name": "Trimble Inc.",
      "sector": "Information Technology",
      "pct_change": -3.357375123287929,
      "conviction": "watching",
      "status": "watching",
      "news_bad": null
    },
    {
      "symbol": "XYZ",
      "name": "Block, Inc.",
      "sector": "Financials",
      "pct_change": -3.3528238204930028,
      "conviction": "watching",
      "status": "watching",
      "news_bad": null
    },
    {
      "symbol": "APP",
      "name": "AppLovin",
      "sector": "Information Technology",
      "pct_change": -3.293754236575049,
      "conviction": "watching",
      "status": "watching",
      "news_bad": null
    },
    {
      "symbol": "COF",
      "name": "Capital One",
      "sector": "Financials",
      "pct_change": -3.278049882077723,
      "conviction": "watching",
      "status": "watching",
      "news_bad": null
    }
  ]
}