{
  "updated_utc": "2026-07-22T17:20:53+00:00",
  "drop_threshold_pct": -5.0,
  "high_conviction_pct": -8.0,
  "stocks": [
    {
      "symbol": "WDAY",
      "name": "Workday, Inc.",
      "sector": "Information Technology",
      "pct_change": -5.567755693348596,
      "conviction": "buy_signal",
      "status": "blocked_news",
      "news_bad": true
    },
    {
      "symbol": "DASH",
      "name": "DoorDash",
      "sector": "Consumer Discretionary",
      "pct_change": -5.1850671921498215,
      "conviction": "buy_signal",
      "status": "bought",
      "news_bad": false
    },
    {
      "symbol": "TYL",
      "name": "Tyler Technologies",
      "sector": "Information Technology",
      "pct_change": -4.757449693948613,
      "conviction": "watching",
      "status": "watching",
      "news_bad": null
    },
    {
      "symbol": "CB",
      "name": "Chubb Limited",
      "sector": "Financials",
      "pct_change": -4.250278210568887,
      "conviction": "watching",
      "status": "watching",
      "news_bad": null
    },
    {
      "symbol": "CRM",
      "name": "Salesforce",
      "sector": "Information Technology",
      "pct_change": -4.133834458556137,
      "conviction": "watching",
      "status": "watching",
      "news_bad": null
    },
    {
      "symbol": "ADSK",
      "name": "Autodesk",
      "sector": "Information Technology",
      "pct_change": -4.011367021329641,
      "conviction": "watching",
      "status": "watching",
      "news_bad": null
    },
    {
      "symbol": "ROP",
      "name": "Roper Technologies",
      "sector": "Information Technology",
      "pct_change": -3.9878570166759344,
      "conviction": "watching",
      "status": "watching",
      "news_bad": null
    },
    {
      "symbol": "COIN",
      "name": "Coinbase",
      "sector": "Financials",
      "pct_change": -3.9692981200235393,
      "conviction": "watching",
      "status": "watching",
      "news_bad": null
    },
    {
      "symbol": "TRMB",
      "name": "Trimble Inc.",
      "sector": "Information Technology",
      "pct_change": -3.9247828491794463,
      "conviction": "watching",
      "status": "watching",
      "news_bad": null
    },
    {
      "symbol": "NTRS",
      "name": "Northern Trust",
      "sector": "Financials",
      "pct_change": -3.8852277835623275,
      "conviction": "watching",
      "status": "watching",
      "news_bad": null
    },
    {
      "symbol": "GLW",
      "name": "Corning Inc.",
      "sector": "Information Technology",
      "pct_change": -3.7682471756537343,
      "conviction": "watching",
      "status": "watching",
      "news_bad": null
    },
    {
      "symbol": "REGN",
      "name": "Regeneron Pharmaceuticals",
      "sector": "Health Care",
      "pct_change": -3.7604251479776427,
      "conviction": "watching",
      "status": "watching",
      "news_bad": null
    },
    {
      "symbol": "APP",
      "name": "AppLovin",
      "sector": "Information Technology",
      "pct_change": -3.620329124841945,
      "conviction": "watching",
      "status": "watching",
      "news_bad": null
    },
    {
      "symbol": "XYZ",
      "name": "Block, Inc.",
      "sector": "Financials",
      "pct_change": -3.5456563467348268,
      "conviction": "watching",
      "status": "watching",
      "news_bad": null
    },
    {
      "symbol": "PLD",
      "name": "Prologis",
      "sector": "Real Estate",
      "pct_change": -3.478055390807765,
      "conviction": "watching",
      "status": "watching",
      "news_bad": null
    }
  ]
}